{"5a611ce094095d0238f7de0948950c73":{"statistic":{"failed":0,"broken":0,"skipped":0,"passed":1,"unknown":0,"total":1},"items":[{"uid":"210c11c71b22169","reportUrl":"https://AfranioAlcantara.github.io/bootcampAutomacao/11//#testresult/210c11c71b22169","status":"passed","time":{"start":1663159169413,"stop":1663159173093,"duration":3680}}]},"98040330ca198b21e49db3a87ad178d4":{"statistic":{"failed":0,"broken":0,"skipped":0,"passed":1,"unknown":0,"total":1},"items":[{"uid":"3583a67a1ade31e","reportUrl":"https://AfranioAlcantara.github.io/bootcampAutomacao/11//#testresult/3583a67a1ade31e","status":"passed","time":{"start":1663186771120,"stop":1663186773642,"duration":2522}}]},"627299ad6c14694140d03683527566fd":{"statistic":{"failed":0,"broken":0,"skipped":0,"passed":1,"unknown":0,"total":1},"items":[{"uid":"3e4f2d02de045190","reportUrl":"https://AfranioAlcantara.github.io/bootcampAutomacao/11//#testresult/3e4f2d02de045190","status":"passed","time":{"start":1663186784798,"stop":1663186785219,"duration":421}}]},"15ee962da7bae49d8bed7abb4abe2bc6":{"statistic":{"failed":0,"broken":0,"skipped":0,"passed":1,"unknown":0,"total":1},"items":[{"uid":"f41e93d3ebbe94a","reportUrl":"https://AfranioAlcantara.github.io/bootcampAutomacao/11//#testresult/f41e93d3ebbe94a","status":"passed","time":{"start":1663186773683,"stop":1663186774627,"duration":944}}]},"a13160fea40222ebd62f472e6f51c7ee":{"statistic":{"failed":0,"broken":0,"skipped":0,"passed":1,"unknown":0,"total":1},"items":[{"uid":"9ce07c3b85ab0889","reportUrl":"https://AfranioAlcantara.github.io/bootcampAutomacao/11//#testresult/9ce07c3b85ab0889","status":"passed","time":{"start":1663186783130,"stop":1663186783434,"duration":304}}]},"c1c8a96d0354d5596ff268aec5269011":{"statistic":{"failed":0,"broken":0,"skipped":0,"passed":1,"unknown":0,"total":1},"items":[{"uid":"a79b28c333c26309","reportUrl":"https://AfranioAlcantara.github.io/bootcampAutomacao/11//#testresult/a79b28c333c26309","status":"passed","time":{"start":1663159173134,"stop":1663159175202,"duration":2068}}]},"07b442d929f7cb2fe405cd4a20aa7134":{"statistic":{"failed":0,"broken":0,"skipped":0,"passed":1,"unknown":0,"total":1},"items":[{"uid":"230dc6d8a160e71e","reportUrl":"https://AfranioAlcantara.github.io/bootcampAutomacao/11//#testresult/230dc6d8a160e71e","status":"passed","time":{"start":1663186774635,"stop":1663186775867,"duration":1232}}]},"2e36eb7d9083c990ca88d591bea1eb07":{"statistic":{"failed":0,"broken":0,"skipped":0,"passed":1,"unknown":0,"total":1},"items":[{"uid":"ca7ef0efb47172bd","reportUrl":"https://AfranioAlcantara.github.io/bootcampAutomacao/11//#testresult/ca7ef0efb47172bd","status":"passed","time":{"start":1663159187554,"stop":1663159200215,"duration":12661}}]},"4ad8377b098393a9931666e23fcf7e20":{"statistic":{"failed":0,"broken":0,"skipped":0,"passed":1,"unknown":0,"total":1},"items":[{"uid":"dd33821b763e0ccd","reportUrl":"https://AfranioAlcantara.github.io/bootcampAutomacao/11//#testresult/dd33821b763e0ccd","status":"passed","time":{"start":1663159178122,"stop":1663159179389,"duration":1267}}]},"7215ee9c7d9dc229d2921a40e899ec5f":{"statistic":{"failed":0,"broken":0,"skipped":0,"passed":1,"unknown":0,"total":1},"items":[{"uid":"1e5c749266c6f3be","reportUrl":"https://AfranioAlcantara.github.io/bootcampAutomacao/11//#testresult/1e5c749266c6f3be","status":"passed","time":{"start":1663159159568,"stop":1663159159614,"duration":46}}]},"cc295448719d4af1e60279d834e0fa78":{"statistic":{"failed":0,"broken":0,"skipped":0,"passed":1,"unknown":0,"total":1},"items":[{"uid":"ec8c53a3220e0b88","reportUrl":"https://AfranioAlcantara.github.io/bootcampAutomacao/11//#testresult/ec8c53a3220e0b88","status":"passed","time":{"start":1663186785545,"stop":1663186785860,"duration":315}}]},"f8ad1b72ebde73c6fbb57a39794b1def":{"statistic":{"failed":0,"broken":0,"skipped":0,"passed":1,"unknown":0,"total":1},"items":[{"uid":"37d8b05864cff51b","reportUrl":"https://AfranioAlcantara.github.io/bootcampAutomacao/11//#testresult/37d8b05864cff51b","status":"passed","time":{"start":1663159148672,"stop":1663159148893,"duration":221}}]},"9833d1a469a025b9859b7292419d1207":{"statistic":{"failed":0,"broken":0,"skipped":0,"passed":1,"unknown":0,"total":1},"items":[{"uid":"3814a4ba6819b88c","reportUrl":"https://AfranioAlcantara.github.io/bootcampAutomacao/11//#testresult/3814a4ba6819b88c","status":"passed","time":{"start":1663186783447,"stop":1663186784708,"duration":1261}}]},"2c2b9eba1b49945d0a729c3d21d6737f":{"statistic":{"failed":0,"broken":0,"skipped":0,"passed":1,"unknown":0,"total":1},"items":[{"uid":"ce201d78a03c858d","reportUrl":"https://AfranioAlcantara.github.io/bootcampAutomacao/11//#testresult/ce201d78a03c858d","status":"passed","time":{"start":1663159147882,"stop":1663159148668,"duration":786}}]},"c3901ec3b57ae9ae7b75ba0732045fe1":{"statistic":{"failed":0,"broken":0,"skipped":0,"passed":1,"unknown":0,"total":1},"items":[{"uid":"1739079dc14d4f0","reportUrl":"https://AfranioAlcantara.github.io/bootcampAutomacao/11//#testresult/1739079dc14d4f0","status":"passed","time":{"start":1663186785224,"stop":1663186785540,"duration":316}}]},"4e48caca453575ce88006bf9f24a600e":{"statistic":{"failed":0,"broken":0,"skipped":0,"passed":1,"unknown":0,"total":1},"items":[{"uid":"27b4e23b8cf213a3","reportUrl":"https://AfranioAlcantara.github.io/bootcampAutomacao/11//#testresult/27b4e23b8cf213a3","status":"passed","time":{"start":1663159179395,"stop":1663159179672,"duration":277}}]}}